zhihubackup/__init__.py
zhihubackup/backup.py
zhihubackup/cli.py
zhihubackup/xzse96.js
zhihubackup-0.2.3.dist-info/LICENSE
zhihubackup-0.2.3.dist-info/METADATA
zhihubackup-0.2.3.dist-info/WHEEL
zhihubackup-0.2.3.dist-info/entry_points.txt
zhihubackup-0.2.3.dist-info/top_level.txt
zhihubackup-0.2.3.dist-info/RECORD
