Metadata-Version: 2.1
Name: zhihubackup
Version: 0.2.3
Summary: Backup your Zhihu contents before quitting Zhihu.
Author-email: Jinzhe Zeng <jinzhe.zeng@rutgers.edu>
License: GNU LESSER GENERAL PUBLIC LICENSE
Project-URL: repository, https://github.com/njzjz/zhihubackup
Keywords: zhihu
Classifier: Programming Language :: Python :: 3.7
Classifier: Programming Language :: Python :: 3.8
Classifier: Programming Language :: Python :: 3.9
Classifier: Programming Language :: Python :: 3.10
Classifier: Programming Language :: Python :: 3.11
Classifier: Operating System :: POSIX :: Linux
Classifier: Operating System :: MacOS :: MacOS X
Classifier: Operating System :: Microsoft :: Windows
Classifier: License :: OSI Approved :: GNU Lesser General Public License v3 (LGPLv3)
Requires-Python: >=3.7
License-File: LICENSE
Requires-Dist: requests
Requires-Dist: tqdm
Requires-Dist: nodejs-wheel-binaries >=20.13.1
Provides-Extra: test
Requires-Dist: pytest ; extra == 'test'
Requires-Dist: pytest-cov ; extra == 'test'
